perceptra_storage/__init__.py
perceptra_storage/base.py
perceptra_storage/factory.py
perceptra_storage/adapters/__init__.py
perceptra_storage/adapters/azure.py
perceptra_storage/adapters/local.py
perceptra_storage/adapters/minio.py
perceptra_storage/adapters/s3.py
perceptra_storage-0.1.2.dist-info/licenses/LICENSE
perceptra_storage-0.1.2.dist-info/METADATA
perceptra_storage-0.1.2.dist-info/WHEEL
perceptra_storage-0.1.2.dist-info/top_level.txt
perceptra_storage-0.1.2.dist-info/RECORD
