Metadata-Version: 2.4
Name: perceptra-storage
Version: 0.1.2
Summary: Unified storage adapter interface for multi-cloud storage backends
Home-page: https://github.com/perceptra/perceptra-storage
Author: Perceptra Team
Author-email: Tannous Geagea <tannousgeagea@hotmail.com>
Maintainer-email: Tannous Geagea <tannousgeagea@hotmail.com>
License: MIT
Project-URL: Homepage, https://github.com/tannousgeagea/perceptra-storage
Project-URL: Documentation, https://docs.perceptra.ai/storage
Project-URL: Repository, https://github.com/tannousgeagea/perceptra-storage
Project-URL: Changelog, https://github.com/tannousgeagea/perceptra-storage/blob/main/CHANGELOG.md
Project-URL: Issue Tracker, https://github.com/tannousgeagea/perceptra-storage/issues
Keywords: storage,cloud,s3,azure,minio,blob,filesystem,adapter,multi-cloud,computer-vision
Classifier: Development Status :: 4 - Beta
Classifier: Intended Audience :: Developers
Classifier: License :: OSI Approved :: MIT License
Classifier: Operating System :: OS Independent
Classifier: Programming Language :: Python
Classifier: Programming Language :: Python :: 3
Classifier: Programming Language :: Python :: 3.9
Classifier: Programming Language :: Python :: 3.10
Classifier: Programming Language :: Python :: 3.11
Classifier: Programming Language :: Python :: 3.12
Classifier: Programming Language :: Python :: 3 :: Only
Classifier: Topic :: Software Development :: Libraries :: Python Modules
Classifier: Topic :: System :: Filesystems
Classifier: Typing :: Typed
Requires-Python: >=3.9
License-File: LICENSE
Requires-Dist: pytest>=7.4.0
Requires-Dist: pytest-cov>=4.1.0
Requires-Dist: pytest-mock>=3.12.0
Provides-Extra: s3
Requires-Dist: boto3<2.0.0,>=1.28.0; extra == "s3"
Requires-Dist: botocore<2.0.0,>=1.31.0; extra == "s3"
Provides-Extra: azure
Requires-Dist: azure-storage-blob<13.0.0,>=12.18.0; extra == "azure"
Requires-Dist: azure-core<2.0.0,>=1.29.0; extra == "azure"
Provides-Extra: minio
Requires-Dist: minio<8.0.0,>=7.2.0; extra == "minio"
Requires-Dist: urllib3<3.0.0,>=2.0.0; extra == "minio"
Provides-Extra: all
Requires-Dist: boto3<2.0.0,>=1.28.0; extra == "all"
Requires-Dist: botocore<2.0.0,>=1.31.0; extra == "all"
Requires-Dist: azure-storage-blob<13.0.0,>=12.18.0; extra == "all"
Requires-Dist: azure-core<2.0.0,>=1.29.0; extra == "all"
Requires-Dist: minio<8.0.0,>=7.2.0; extra == "all"
Requires-Dist: urllib3<3.0.0,>=2.0.0; extra == "all"
Provides-Extra: dev
Requires-Dist: pytest>=7.4.0; extra == "dev"
Requires-Dist: pytest-cov>=4.1.0; extra == "dev"
Requires-Dist: pytest-mock>=3.12.0; extra == "dev"
Requires-Dist: pytest-asyncio>=0.21.0; extra == "dev"
Requires-Dist: black>=23.12.0; extra == "dev"
Requires-Dist: isort>=5.13.0; extra == "dev"
Requires-Dist: flake8>=6.1.0; extra == "dev"
Requires-Dist: mypy>=1.7.0; extra == "dev"
Requires-Dist: pylint>=3.0.0; extra == "dev"
Requires-Dist: pre-commit>=3.5.0; extra == "dev"
Requires-Dist: tox>=4.11.0; extra == "dev"
Provides-Extra: docs
Requires-Dist: sphinx>=7.2.0; extra == "docs"
Requires-Dist: sphinx-rtd-theme>=2.0.0; extra == "docs"
Requires-Dist: sphinx-autodoc-typehints>=1.25.0; extra == "docs"
Requires-Dist: myst-parser>=2.0.0; extra == "docs"
Provides-Extra: test-s3
Requires-Dist: boto3<2.0.0,>=1.28.0; extra == "test-s3"
Requires-Dist: moto[s3]>=4.2.0; extra == "test-s3"
Provides-Extra: test-azure
Requires-Dist: azure-storage-blob<13.0.0,>=12.18.0; extra == "test-azure"
Provides-Extra: test-minio
Requires-Dist: minio<8.0.0,>=7.2.0; extra == "test-minio"
Provides-Extra: dev-all
Requires-Dist: perceptra-storage[all,dev,docs]; extra == "dev-all"
Dynamic: author
Dynamic: home-page
Dynamic: license-file
Dynamic: requires-python
